oarepo_model/__init__.py
oarepo_model/api.py
oarepo_model/builder.py
oarepo_model/c3linearize.py
oarepo_model/cli.py
oarepo_model/errors.py
oarepo_model/model.py
oarepo_model/py.typed
oarepo_model/register.py
oarepo_model/sorter.py
oarepo_model/utils.py
oarepo_model/customizations/__init__.py
oarepo_model/customizations/add_base_class.py
oarepo_model/customizations/add_class.py
oarepo_model/customizations/add_class_field.py
oarepo_model/customizations/add_class_list.py
oarepo_model/customizations/add_dictionary.py
oarepo_model/customizations/add_entry_point.py
oarepo_model/customizations/add_facet_group.py
oarepo_model/customizations/add_file_to_module.py
oarepo_model/customizations/add_json_file.py
oarepo_model/customizations/add_list.py
oarepo_model/customizations/add_module.py
oarepo_model/customizations/add_to_dictionary.py
oarepo_model/customizations/add_to_list.py
oarepo_model/customizations/add_to_module.py
oarepo_model/customizations/base.py
oarepo_model/customizations/change_base.py
oarepo_model/customizations/copy_file.py
oarepo_model/customizations/patch_json_file.py
oarepo_model/customizations/prepend_mixin.py
oarepo_model/customizations/high_level/__init__.py
oarepo_model/customizations/high_level/add_export.py
oarepo_model/customizations/high_level/add_import.py
oarepo_model/customizations/high_level/add_link.py
oarepo_model/customizations/high_level/add_pid_relation.py
oarepo_model/customizations/high_level/add_search_fields.py
oarepo_model/customizations/high_level/add_service_component.py
oarepo_model/customizations/high_level/index_mapping.py
oarepo_model/customizations/high_level/index_settings.py
oarepo_model/customizations/high_level/set_permission_policy.py
oarepo_model/datatypes/__init__.py
oarepo_model/datatypes/base.py
oarepo_model/datatypes/boolean.py
oarepo_model/datatypes/collections.py
oarepo_model/datatypes/date.py
oarepo_model/datatypes/entrypoints.py
oarepo_model/datatypes/multilingual.py
oarepo_model/datatypes/numbers.py
oarepo_model-0.1.0.dev50.dist-info/METADATA
oarepo_model-0.1.0.dev50.dist-info/WHEEL
oarepo_model-0.1.0.dev50.dist-info/entry_points.txt
oarepo_model-0.1.0.dev50.dist-info/licenses/LICENSE
oarepo_model-0.1.0.dev50.dist-info/RECORD
