Metadata-Version: 2.4
Name: oarepo-model
Version: 0.1.0.dev50
Summary: Add your description here
Project-URL: Homepage, https://github.com/oarepo/oarepo-model
Author-email: Mirek Simek <miroslav.simek@gmail.com>
License-File: LICENSE
Requires-Python: <3.15,>=3.13
Requires-Dist: deepmerge
Requires-Dist: deepmerge>=2.0
Requires-Dist: dotenv>=0.9.9
Requires-Dist: graphlib
Requires-Dist: marshmallow-i18n-messages>=0.1.0
Requires-Dist: oarepo-runtime<3.0.0,>=2.0.0dev5
Requires-Dist: oarepo[rdm,tests]<15.0.0,>=13.0.0
Requires-Dist: oarepo[rdm,tests]<15.0.0,>=14.0.0
Provides-Extra: dev
Requires-Dist: oarepo-invenio-typing-stubs; extra == 'dev'
Requires-Dist: ruff>=0.11.13; extra == 'dev'
Requires-Dist: types-pyyaml; extra == 'dev'
Provides-Extra: oarepo14
Requires-Dist: oarepo[rdm]<15,>=14; extra == 'oarepo14'
Provides-Extra: tests
Requires-Dist: pytest-invenio; extra == 'tests'
